create_container_vscode_project/__init__.py
create_container_vscode_project/main.py
create_container_vscode_project-0.0.3.dist-info/METADATA
create_container_vscode_project-0.0.3.dist-info/WHEEL
create_container_vscode_project-0.0.3.dist-info/entry_points.txt
create_container_vscode_project-0.0.3.dist-info/RECORD
