Metadata-Version: 2.3
Name: create-container-vscode-project
Version: 0.0.3
Summary: Create template file by project name
Author: CWKSC
Classifier: License :: OSI Approved :: MIT License
Classifier: Programming Language :: Python :: 3
Requires-Python: >=3.8
